insightlog/__init__.py
insightlog/insight_logger.py
InsightLogger-1.2.3.dist-info/LICENSE
InsightLogger-1.2.3.dist-info/METADATA
InsightLogger-1.2.3.dist-info/WHEEL
InsightLogger-1.2.3.dist-info/top_level.txt
InsightLogger-1.2.3.dist-info/RECORD
