Metadata-Version: 2.1
Name: InsightLogger
Version: 1.2.3
Summary: A customizable logging utility with enhanced features for developers.
Home-page: https://github.com/VelisCore/InsightLogger
Download-URL: https://github.com/VelisCore/InsightLogger/archive/refs/tags/v1.2.3.tar.gz
Author: VelisCore
Author-email: velis.help@web.de
License: MIT
Project-URL: Bug Tracker, https://github.com/VelisCore/InsightLogger/issues
Project-URL: Documentation, https://github.com/VelisCore/InsightLogger/wiki
Project-URL: Source Code, https://github.com/VelisCore/InsightLogger
Keywords: logging,log,logger,developer tools,performance monitoring,visualization
Classifier: Development Status :: 5 - Production/Stable
Classifier: Intended Audience :: Developers
Classifier: Topic :: Software Development :: Libraries :: Python Modules
Classifier: Topic :: Software Development :: Libraries
Classifier: License :: OSI Approved :: MIT License
Classifier: Programming Language :: Python :: 3
Classifier: Programming Language :: Python :: 3.9
Classifier: Programming Language :: Python :: 3.10
Classifier: Programming Language :: Python :: 3.11
Classifier: Operating System :: OS Independent
Requires-Python: >=3.9
License-File: LICENSE
Requires-Dist: termcolor
Requires-Dist: matplotlib
Requires-Dist: tabulate
Requires-Dist: psutil
Requires-Dist: tqdm
